nba_injury_report/__init__.py
nba_injury_report/_client.py
nba_injury_report/constants.py
nba_injury_report/models.py
nba_injury_report/report.py
nba_injury_report-0.1.0.dist-info/WHEEL
nba_injury_report-0.1.0.dist-info/entry_points.txt
nba_injury_report-0.1.0.dist-info/METADATA
nba_injury_report-0.1.0.dist-info/RECORD
