Metadata-Version: 2.4
Name: nba-injury-report
Version: 0.1.0
Summary: Fetch and parse official NBA injury reports
Keywords: nba,basketball,injury,report,sports,data
License-Expression: AGPL-3.0-or-later
Requires-Dist: httpx>=0.28.1
Requires-Dist: pydantic>=2.0.0
Requires-Dist: pymupdf>=1.26.7
Requires-Dist: pandas>=2.3.3 ; extra == 'pandas'
Requires-Dist: tabulate>=0.9.0 ; extra == 'tabulate'
Requires-Python: >=3.12
Project-URL: Homepage, https://github.com/mkeenan195/nba-injury-report
Project-URL: Issues, https://github.com/mkeenan195/nba-injury-report/issues
Project-URL: Repository, https://github.com/mkeenan195/nba-injury-report
Provides-Extra: pandas
Provides-Extra: tabulate
